MANIFEST.in
README.md
setup.py
docs/HISTORY.txt
docs/README.txt
eea/__init__.py
eea.eggmonkeytesttarget.egg-info/PKG-INFO
eea.eggmonkeytesttarget.egg-info/SOURCES.txt
eea.eggmonkeytesttarget.egg-info/dependency_links.txt
eea.eggmonkeytesttarget.egg-info/namespace_packages.txt
eea.eggmonkeytesttarget.egg-info/not-zip-safe
eea.eggmonkeytesttarget.egg-info/requires.txt
eea.eggmonkeytesttarget.egg-info/top_level.txt
eea/eggmonkeytesttarget/__init__.py
eea/eggmonkeytesttarget/version.txt