Metadata-Version: 1.1
Name: eea.eggmonkeytesttarget
Version: 5.7
Summary: A dummy package to test eea.eggmonkey
Home-page: https://svn.eionet.europa.eu/repositories/Zope/trunk/eea.eggmonkeytesttarget
Author: Tiberiu Ichim
Author-email: tiberiu@eaudeweb.ro
License: GPL
Keywords: buildout
Platform: UNKNOWN
Classifier: Programming Language :: Python
